nonebot_plugin_course/__init__.py
nonebot_plugin_course/template.py
nonebot_plugin_course/utils.py
nonebot_plugin_course-0.1.9.dist-info/LICENSE
nonebot_plugin_course-0.1.9.dist-info/METADATA
nonebot_plugin_course-0.1.9.dist-info/WHEEL
nonebot_plugin_course-0.1.9.dist-info/top_level.txt
nonebot_plugin_course-0.1.9.dist-info/RECORD
