Metadata-Version: 2.1
Name: nonebot-plugin-course
Version: 0.1.9
Summary: A plugin for nonebot to show course information
Home-page: https://github.com/InariInDream/nonebot_plugin_course
Author: InariInDream
Author-email: inariindream@163.com
Classifier: Programming Language :: Python :: 3
Classifier: License :: OSI Approved :: MIT License
Classifier: Operating System :: OS Independent
License-File: LICENSE
Requires-Dist: pydantic (>=1.9.0)
Requires-Dist: Pillow (>=9.0.0)
Requires-Dist: nonebot-plugin-PicMenu (>=0.1.5)
Requires-Dist: nonebot-plugin-apscheduler (>=0.1.3)
Requires-Dist: nonebot-adapter-onebot (>=2.0.0-beta.1)
Requires-Dist: nonebot2 (>=2.0.0-beta.4)
